{
  "content": [
    {
      "content": null,
      "created": "2021-07-13T10:24:52.931135Z",
      "format": null,
      "last_modified": "2021-07-13T10:23:59.014713Z",
      "mimetype": "text/markdown",
      "name": "testfile.md",
      "path": "content/PremiereNSI/testfile.md",
      "size": 7,
      "type": "file",
      "writable": true
    }
  ],
  "created": "2021-07-13T10:24:52.931135Z",
  "format": "json",
  "last_modified": "2021-07-13T10:24:52.931135Z",
  "mimetype": null,
  "name": "PremiereNSI",
  "path": "content/PremiereNSI",
  "size": null,
  "type": "directory",
  "writable": true
}